myteste/__init__.py
myteste/run.py
pyreportjasper/__init__.py
pyreportjasper/application_class_path.py
pyreportjasper/config.py
pyreportjasper/db.py
pyreportjasper/pyreportjasper.py
pyreportjasper/report.py
pyreportjasper/libs/FastInfoset-1.2.15.jar
pyreportjasper/libs/SparseBitSet-1.2.jar
pyreportjasper/libs/acesseonline-1.0.jar
pyreportjasper/libs/ant-1.10.11.jar
pyreportjasper/libs/ant-launcher-1.10.11.jar
pyreportjasper/libs/antlr-2.7.5.jar
pyreportjasper/libs/avalon-framework-impl-4.2.0.jar
pyreportjasper/libs/barbecue-1.5-beta1.jar
pyreportjasper/libs/barcode4j-2.1.jar
pyreportjasper/libs/batik-anim-1.17.jar
pyreportjasper/libs/batik-awt-util-1.17.jar
pyreportjasper/libs/batik-bridge-1.17.jar
pyreportjasper/libs/batik-constants-1.17.jar
pyreportjasper/libs/batik-css-1.17.jar
pyreportjasper/libs/batik-dom-1.17.jar
pyreportjasper/libs/batik-ext-1.17.jar
pyreportjasper/libs/batik-gvt-1.17.jar
pyreportjasper/libs/batik-i18n-1.17.jar
pyreportjasper/libs/batik-parser-1.17.jar
pyreportjasper/libs/batik-script-1.17.jar
pyreportjasper/libs/batik-shared-resources-1.17.jar
pyreportjasper/libs/batik-svg-dom-1.17.jar
pyreportjasper/libs/batik-svggen-1.17.jar
pyreportjasper/libs/batik-transcoder-1.17.jar
pyreportjasper/libs/batik-util-1.17.jar
pyreportjasper/libs/batik-xml-1.17.jar
pyreportjasper/libs/byte-buddy-1.10.17.jar
pyreportjasper/libs/cdt-java-client-4.0.0.jar
pyreportjasper/libs/classmate-1.5.1.jar
pyreportjasper/libs/commons-beanutils-1.9.4.jar
pyreportjasper/libs/commons-cli-1.0.jar
pyreportjasper/libs/commons-codec-1.15.jar
pyreportjasper/libs/commons-collections-3.2.2.jar
pyreportjasper/libs/commons-collections4-4.2.jar
pyreportjasper/libs/commons-compress-1.21.jar
pyreportjasper/libs/commons-dbcp-1.2.jar
pyreportjasper/libs/commons-digester-2.1.jar
pyreportjasper/libs/commons-discovery-0.2.jar
pyreportjasper/libs/commons-io-2.11.0.jar
pyreportjasper/libs/commons-lang-1.0.jar
pyreportjasper/libs/commons-lang-2.4.jar
pyreportjasper/libs/commons-lang3-3.11.jar
pyreportjasper-2.1.4.dist-info/LICENSE
pyreportjasper-2.1.4.dist-info/METADATA
pyreportjasper-2.1.4.dist-info/WHEEL
pyreportjasper-2.1.4.dist-info/top_level.txt
pyreportjasper-2.1.4.dist-info/RECORD
