Metadata-Version: 2.1
Name: pyreportjasper
Version: 2.1.4
Summary: This package aims to be a solution to compile and process JasperReports (.jrxml & .jasper files).
Home-page: https://github.com/acesseonline/pyreportjasper
Download-URL: https://pypi.python.org/pypi/pyreportjasper/2.1.4
Author: Jadson Bonfim Ribeiro
Author-email: contato@jadsonbr.com.br
Maintainer: Jadson Bonfim Ribeiro
Maintainer-email: contato@jadsonbr.com.br
License: GPLv3
Project-URL: Documentation, https://pyreportjasper.readthedocs.io/en/master/
Project-URL: Code, https://github.com/acesseonline/pyreportjasper
Project-URL: Issue tracker, https://github.com/acesseonline/pyreportjasper/issues
Keywords: report jasper python
Platform: Operating System :: Microsoft :: Windows
Platform: Operating System :: POSIX
Platform: Operating System :: Unix
Platform: Operating System :: MacOS
Classifier: Intended Audience :: Developers
Classifier: Operating System :: OS Independent
Classifier: Topic :: Software Development :: Libraries :: Python Modules
Classifier: License :: OSI Approved :: GNU General Public License v3 (GPLv3)
Classifier: Programming Language :: Python :: 3.8
Classifier: Programming Language :: Python :: 3.9
Classifier: Programming Language :: Python :: 3.10
Classifier: Programming Language :: Python :: 3.11
Requires-Python: >=3.7
License-File: LICENSE
Requires-Dist: jpype1
Requires-Dist: pillow
Provides-Extra: docs
Requires-Dist: readthedocs-sphinx-ext ; extra == 'docs'
Requires-Dist: sphinx ; extra == 'docs'
Requires-Dist: sphinx-rtd-theme ; extra == 'docs'
Requires-Dist: recommonmark ; extra == 'docs'
Requires-Dist: commonmark ; extra == 'docs'
Requires-Dist: mock ; extra == 'docs'
Requires-Dist: docutils ; extra == 'docs'
Requires-Dist: Pygments ; extra == 'docs'
Requires-Dist: pillow ; extra == 'docs'
